<PAMDataset>
  <PAMRasterBand band="1">
    <Histograms>
      <HistItem>
        <HistMin>-0.5</HistMin>
        <HistMax>254.5</HistMax>
        <BucketCount>255</BucketCount>
        <IncludeOutOfRange>1</IncludeOutOfRange>
        <Approximate>0</Approximate>
        <HistCounts>0|0|0|0|0|0|0|0|0|0|0|0|0|0|0|0|0|0|0|0|0|0|0|0|0|0|0|0|0|0|0|0|0|0|0|0|0|0|0|0|0|0|0|0|0|0|0|0|0|0|0|0|0|0|0|0|0|0|0|0|0|0|0|0|0|0|0|0|0|0|0|0|0|0|0|0|0|0|0|1|2|3|5|5|19|35|51|76|74|120|138|192|236|331|377|460|504|662|661|819|824|967|1031|1127|1168|1244|1262|1326|1381|1400|1419|1429|1345|1359|1405|1322|1328|1281|1265|1214|1203|1158|1169|1020|1045|1050|1030|1008|969|944|904|883|882|855|784|830|834|740|755|748|712|732|664|709|696|708|684|704|645|675|679|678|669|669|608|641|643|590|592|644|630|651|587|620|642|609|562|635|635|567|631|621|646|635|596|603|632|625|619|644|641|625|644|671|654|659|678|712|676|698|679|715|724|759|835|792|783|812|875|901|980|981|1018|1013|1007|1114|1104|1051|1126|1147|1220|1136|1194|1151|1201|1171|1230|1319|1364|1311|1371|1489|1515|1516|1622|1709|1778|1888|2018|2122|2230|2416|2415|2538|2881|3125|3380|3657|4326|4713|6062|7501|11191|14028|28003|36469|81556|102190|201799|205615|292621|208938|198718|92207|79786</HistCounts>
      </HistItem>
    </Histograms>
    <Metadata>
      <MDI key="STATISTICS_COUNT">1727175.000000</MDI>
      <MDI key="STATISTICS_COVARIANCES">656.1807196756109,662.2340213606094,629.6992433710536</MDI>
      <MDI key="STATISTICS_EXCLUDEDVALUES"></MDI>
      <MDI key="STATISTICS_MAXIMUM">254</MDI>
      <MDI key="STATISTICS_MEAN">242.89963900589</MDI>
      <MDI key="STATISTICS_MEDIAN">250.000000</MDI>
      <MDI key="STATISTICS_MINIMUM">79</MDI>
      <MDI key="STATISTICS_SKIPFACTORX">1</MDI>
      <MDI key="STATISTICS_SKIPFACTORY">1</MDI>
      <MDI key="STATISTICS_STDDEV">25.616024665736</MDI>
    </Metadata>
  </PAMRasterBand>
  <PAMRasterBand band="2">
    <Histograms>
      <HistItem>
        <HistMin>-0.5</HistMin>
        <HistMax>254.5</HistMax>
        <BucketCount>255</BucketCount>
        <IncludeOutOfRange>1</IncludeOutOfRange>
        <Approximate>0</Approximate>
        <HistCounts>0|0|0|0|0|0|0|0|0|0|0|0|0|0|0|0|0|0|0|0|0|0|0|0|0|0|0|0|0|0|0|0|0|0|0|0|0|0|0|0|0|0|0|0|0|0|0|0|0|0|0|0|0|0|0|0|0|0|0|0|0|0|0|0|0|0|0|0|0|0|0|0|0|0|0|0|0|0|3|1|8|7|13|19|37|47|59|91|121|172|220|283|317|478|470|604|697|798|820|1000|1047|1116|1151|1312|1225|1359|1365|1354|1389|1397|1432|1387|1328|1318|1290|1307|1247|1202|1170|1134|1179|1093|1022|982|994|958|971|933|878|886|823|853|850|844|779|775|732|710|663|678|727|691|745|657|683|673|755|679|702|751|695|704|745|705|747|753|739|693|705|747|714|716|734|709|677|683|712|664|657|664|669|635|636|650|657|704|644|651|680|684|721|664|660|662|651|662|674|709|724|736|736|695|760|705|807|771|728|787|795|806|824|761|849|861|843|860|905|911|903|998|958|1005|1068|1079|1090|1064|1098|1110|1182|1194|1223|1296|1297|1284|1436|1537|1606|1647|1699|1832|1996|2141|2256|2288|2577|2669|3029|3365|3744|4397|5148|6041|8877|11144|20451|27604|66100|86097|197818|208803|330743|226823|219148|88902|68907</HistCounts>
      </HistItem>
    </Histograms>
    <Metadata>
      <MDI key="STATISTICS_COUNT">1727175.000000</MDI>
      <MDI key="STATISTICS_COVARIANCES">662.2340213606094,679.2572018034942,649.1963692968991</MDI>
      <MDI key="STATISTICS_EXCLUDEDVALUES"></MDI>
      <MDI key="STATISTICS_MAXIMUM">254</MDI>
      <MDI key="STATISTICS_MEAN">242.99520372862</MDI>
      <MDI key="STATISTICS_MEDIAN">250.000000</MDI>
      <MDI key="STATISTICS_MINIMUM">78</MDI>
      <MDI key="STATISTICS_SKIPFACTORX">1</MDI>
      <MDI key="STATISTICS_SKIPFACTORY">1</MDI>
      <MDI key="STATISTICS_STDDEV">26.062563223971</MDI>
    </Metadata>
  </PAMRasterBand>
  <PAMRasterBand band="3">
    <Histograms>
      <HistItem>
        <HistMin>-0.5</HistMin>
        <HistMax>252.5</HistMax>
        <BucketCount>253</BucketCount>
        <IncludeOutOfRange>1</IncludeOutOfRange>
        <Approximate>0</Approximate>
        <HistCounts>0|0|0|0|0|0|0|0|0|0|0|0|0|0|0|0|0|0|0|0|0|0|0|0|0|0|0|0|0|0|0|0|0|0|0|0|0|0|0|0|0|0|0|0|0|0|0|0|0|0|0|0|0|0|0|0|0|0|0|0|0|0|0|0|0|0|0|0|0|0|0|0|0|0|1|1|2|11|10|24|22|46|73|107|109|189|231|328|424|477|579|754|816|932|1055|1153|1276|1343|1402|1420|1537|1572|1535|1618|1615|1604|1566|1437|1476|1428|1340|1378|1276|1282|1269|1220|1159|1172|1089|1053|1003|974|992|940|888|843|869|840|844|862|823|763|744|793|755|759|702|686|707|738|689|727|677|672|661|627|697|667|664|680|663|649|635|632|660|621|623|666|630|579|618|597|654|619|553|617|671|629|649|664|616|630|666|590|673|676|673|644|659|671|697|722|688|707|701|754|758|739|773|752|778|756|796|820|820|803|877|874|907|893|924|971|956|958|1027|1064|1099|1130|1207|1233|1161|1305|1315|1421|1427|1469|1548|1768|1874|2024|2229|2504|2783|3227|3710|4559|5447|7714|9926|16479|22222|38267|42404|53552|93382|92429|98486|112841|215671|204917|242216|143764|111303|41172|22767|5499|2687|448|210|23|16|0|1</HistCounts>
      </HistItem>
    </Histograms>
    <Metadata>
      <MDI key="STATISTICS_COUNT">1727175.000000</MDI>
      <MDI key="STATISTICS_COVARIANCES">629.6992433710536,649.1963692968991,634.1426971332509</MDI>
      <MDI key="STATISTICS_EXCLUDEDVALUES"></MDI>
      <MDI key="STATISTICS_MAXIMUM">252</MDI>
      <MDI key="STATISTICS_MEAN">231.43154804811</MDI>
      <MDI key="STATISTICS_MEDIAN">238.000000</MDI>
      <MDI key="STATISTICS_MINIMUM">74</MDI>
      <MDI key="STATISTICS_SKIPFACTORX">1</MDI>
      <MDI key="STATISTICS_SKIPFACTORY">1</MDI>
      <MDI key="STATISTICS_STDDEV">25.182190078173</MDI>
    </Metadata>
  </PAMRasterBand>
</PAMDataset>
